luscious/__init__.py
luscious/luscious.py
luscious/queries.py
luscious-1.1.4.dist-info/LICENSE
luscious-1.1.4.dist-info/METADATA
luscious-1.1.4.dist-info/WHEEL
luscious-1.1.4.dist-info/top_level.txt
luscious-1.1.4.dist-info/RECORD
